mojo/credentials/__init__.py
mojo/credentials/apitokencredential.py
mojo/credentials/awsaccesskeycredential.py
mojo/credentials/azureclientsecretcredential.py
mojo/credentials/basecredential.py
mojo/credentials/basiccredential.py
mojo/credentials/credentialmanager.py
mojo/credentials/personalapitokencredential.py
mojo/credentials/publickeycredential.py
mojo/credentials/sshcredential.py
mojo/credentials/wifichoicecredential.py
mojo_credentials-2.0.2.dist-info/LICENSE.txt
mojo_credentials-2.0.2.dist-info/METADATA
mojo_credentials-2.0.2.dist-info/WHEEL
mojo_credentials-2.0.2.dist-info/RECORD
