Metadata-Version: 2.1
Name: mojo-credentials
Version: 2.0.2
Summary: Automation Mojo Credentials Package
License: LICENSE.txt
Keywords: python
Requires-Python: >=3.9,<4.0
Classifier: License :: OSI Approved :: MIT License
Classifier: License :: Other/Proprietary License
Classifier: Operating System :: POSIX
Classifier: Programming Language :: Python :: 3
Classifier: Programming Language :: Python :: 3.9
Classifier: Programming Language :: Python :: 3.10
Classifier: Programming Language :: Python :: 3.11
Classifier: Programming Language :: Python :: 3.12
Requires-Dist: mojo-errors (>=2.0.0,<2.1.0)
Requires-Dist: pyyaml (>=6.0.2,<7.0.0)
